gb32960/__init__.py
gb32960-0.1.0.dist-info/LICENSE
gb32960-0.1.0.dist-info/METADATA
gb32960-0.1.0.dist-info/WHEEL
gb32960-0.1.0.dist-info/top_level.txt
gb32960-0.1.0.dist-info/RECORD
