Metadata-Version: 2.1
Name: gb32960
Version: 0.1.0
Summary: GB32960 protocol tools, including encoding/decoding, and validation suite.
Home-page: https://github.com/matrixji/python-gb32960
Author: "Ji Bin"
Author-email: Ji Bin <matrixji@live.com>
Maintainer-email: Ji Bin <matrixji@live.com>
License: MIT License
Project-URL: Homepage, https://github.com/matrixji/python-gb32960
Project-URL: Home-page, https://github.com/matrixji/python-gb32960
Project-URL: Repository, https://github.com/matrixji/python-gb32960.git
Project-URL: Issues, https://github.com/matrixji/python-gb32960/issues
Keywords: gb32960,protocol,vehicle,telematics
Classifier: Development Status :: 3 - Alpha
Classifier: License :: OSI Approved :: MIT License
Classifier: Programming Language :: Python :: 3
Requires-Python: >=3.8
License-File: LICENSE
